[{"PropertyID":1,"CaseMasterID":946,"PropertyType":"Cash","EstimatedValue":181094},{"PropertyID":2,"CaseMasterID":140,"PropertyType":"Documents","EstimatedValue":23869},{"PropertyID":3,"CaseMasterID":679,"PropertyType":"Laptop","EstimatedValue":70835},{"PropertyID":4,"CaseMasterID":554,"PropertyType":"Mobile","EstimatedValue":173025},{"PropertyID":5,"CaseMasterID":19,"PropertyType":"Jewellery","EstimatedValue":260765},{"PropertyID":6,"CaseMasterID":123,"PropertyType":"Cash","EstimatedValue":332192},{"PropertyID":7,"CaseMasterID":24,"PropertyType":"Documents","EstimatedValue":152676},{"PropertyID":8,"CaseMasterID":248,"PropertyType":"Cash","EstimatedValue":321221},{"PropertyID":9,"CaseMasterID":979,"PropertyType":"Cash","EstimatedValue":215692},{"PropertyID":10,"CaseMasterID":174,"PropertyType":"Vehicles","EstimatedValue":58496},{"PropertyID":11,"CaseMasterID":214,"PropertyType":"Laptop","EstimatedValue":56376},{"PropertyID":12,"CaseMasterID":722,"PropertyType":"Mobile","EstimatedValue":80638},{"PropertyID":13,"CaseMasterID":573,"PropertyType":"Jewellery","EstimatedValue":458479},{"PropertyID":14,"CaseMasterID":769,"PropertyType":"Mobile","EstimatedValue":18127},{"PropertyID":15,"CaseMasterID":885,"PropertyType":"Jewellery","EstimatedValue":126325},{"PropertyID":16,"CaseMasterID":81,"PropertyType":"Cash","EstimatedValue":436857},{"PropertyID":17,"CaseMasterID":514,"PropertyType":"Documents","EstimatedValue":138648},{"PropertyID":18,"CaseMasterID":146,"PropertyType":"Mobile","EstimatedValue":466841},{"PropertyID":19,"CaseMasterID":378,"PropertyType":"Documents","EstimatedValue":37210},{"PropertyID":20,"CaseMasterID":172,"PropertyType":"Laptop","EstimatedValue":325211},{"PropertyID":21,"CaseMasterID":655,"PropertyType":"Jewellery","EstimatedValue":329341},{"PropertyID":22,"CaseMasterID":417,"PropertyType":"Laptop","EstimatedValue":70345},{"PropertyID":23,"CaseMasterID":373,"PropertyType":"Documents","EstimatedValue":118885},{"PropertyID":24,"CaseMasterID":210,"PropertyType":"Laptop","EstimatedValue":458215},{"PropertyID":25,"CaseMasterID":204,"PropertyType":"Vehicles","EstimatedValue":148861},{"PropertyID":26,"CaseMasterID":759,"PropertyType":"Jewellery","EstimatedValue":422108},{"PropertyID":27,"CaseMasterID":79,"PropertyType":"Jewellery","EstimatedValue":147709},{"PropertyID":28,"CaseMasterID":316,"PropertyType":"Mobile","EstimatedValue":384429},{"PropertyID":29,"CaseMasterID":773,"PropertyType":"Vehicles","EstimatedValue":402485},{"PropertyID":30,"CaseMasterID":861,"PropertyType":"Mobile","EstimatedValue":283837},{"PropertyID":31,"CaseMasterID":900,"PropertyType":"Cash","EstimatedValue":351367},{"PropertyID":32,"CaseMasterID":529,"PropertyType":"Documents","EstimatedValue":367746},{"PropertyID":33,"CaseMasterID":528,"PropertyType":"Documents","EstimatedValue":165013},{"PropertyID":34,"CaseMasterID":702,"PropertyType":"Mobile","EstimatedValue":284095},{"PropertyID":35,"CaseMasterID":682,"PropertyType":"Vehicles","EstimatedValue":60135},{"PropertyID":36,"CaseMasterID":200,"PropertyType":"Vehicles","EstimatedValue":360025},{"PropertyID":37,"CaseMasterID":178,"PropertyType":"Documents","EstimatedValue":35471},{"PropertyID":38,"CaseMasterID":627,"PropertyType":"Documents","EstimatedValue":52323},{"PropertyID":39,"CaseMasterID":128,"PropertyType":"Cash","EstimatedValue":199615},{"PropertyID":40,"CaseMasterID":186,"PropertyType":"Laptop","EstimatedValue":383752},{"PropertyID":41,"CaseMasterID":375,"PropertyType":"Laptop","EstimatedValue":452424},{"PropertyID":42,"CaseMasterID":576,"PropertyType":"Documents","EstimatedValue":327768},{"PropertyID":43,"CaseMasterID":280,"PropertyType":"Vehicles","EstimatedValue":14401},{"PropertyID":44,"CaseMasterID":634,"PropertyType":"Mobile","EstimatedValue":210592},{"PropertyID":45,"CaseMasterID":502,"PropertyType":"Laptop","EstimatedValue":254114},{"PropertyID":46,"CaseMasterID":736,"PropertyType":"Vehicles","EstimatedValue":97654},{"PropertyID":47,"CaseMasterID":958,"PropertyType":"Vehicles","EstimatedValue":402117},{"PropertyID":48,"CaseMasterID":995,"PropertyType":"Laptop","EstimatedValue":14831},{"PropertyID":49,"CaseMasterID":944,"PropertyType":"Laptop","EstimatedValue":189607},{"PropertyID":50,"CaseMasterID":500,"PropertyType":"Laptop","EstimatedValue":219067},{"PropertyID":51,"CaseMasterID":255,"PropertyType":"Laptop","EstimatedValue":274625},{"PropertyID":52,"CaseMasterID":909,"PropertyType":"Jewellery","EstimatedValue":381825},{"PropertyID":53,"CaseMasterID":832,"PropertyType":"Cash","EstimatedValue":346358},{"PropertyID":54,"CaseMasterID":277,"PropertyType":"Laptop","EstimatedValue":408122},{"PropertyID":55,"CaseMasterID":963,"PropertyType":"Documents","EstimatedValue":327223},{"PropertyID":56,"CaseMasterID":814,"PropertyType":"Documents","EstimatedValue":309809},{"PropertyID":57,"CaseMasterID":128,"PropertyType":"Laptop","EstimatedValue":254006},{"PropertyID":58,"CaseMasterID":910,"PropertyType":"Documents","EstimatedValue":161656},{"PropertyID":59,"CaseMasterID":778,"PropertyType":"Mobile","EstimatedValue":86317},{"PropertyID":60,"CaseMasterID":569,"PropertyType":"Mobile","EstimatedValue":286411},{"PropertyID":61,"CaseMasterID":571,"PropertyType":"Jewellery","EstimatedValue":183911},{"PropertyID":62,"CaseMasterID":904,"PropertyType":"Vehicles","EstimatedValue":248134},{"PropertyID":63,"CaseMasterID":472,"PropertyType":"Vehicles","EstimatedValue":360640},{"PropertyID":64,"CaseMasterID":711,"PropertyType":"Mobile","EstimatedValue":444772},{"PropertyID":65,"CaseMasterID":149,"PropertyType":"Jewellery","EstimatedValue":102692},{"PropertyID":66,"CaseMasterID":849,"PropertyType":"Jewellery","EstimatedValue":162447},{"PropertyID":67,"CaseMasterID":992,"PropertyType":"Mobile","EstimatedValue":67900},{"PropertyID":68,"CaseMasterID":477,"PropertyType":"Mobile","EstimatedValue":325576},{"PropertyID":69,"CaseMasterID":576,"PropertyType":"Documents","EstimatedValue":107195},{"PropertyID":70,"CaseMasterID":347,"PropertyType":"Cash","EstimatedValue":177856},{"PropertyID":71,"CaseMasterID":19,"PropertyType":"Laptop","EstimatedValue":478603},{"PropertyID":72,"CaseMasterID":35,"PropertyType":"Vehicles","EstimatedValue":166804},{"PropertyID":73,"CaseMasterID":81,"PropertyType":"Vehicles","EstimatedValue":15041},{"PropertyID":74,"CaseMasterID":599,"PropertyType":"Laptop","EstimatedValue":360246},{"PropertyID":75,"CaseMasterID":889,"PropertyType":"Jewellery","EstimatedValue":464647},{"PropertyID":76,"CaseMasterID":350,"PropertyType":"Laptop","EstimatedValue":98039},{"PropertyID":77,"CaseMasterID":347,"PropertyType":"Cash","EstimatedValue":454163},{"PropertyID":78,"CaseMasterID":261,"PropertyType":"Mobile","EstimatedValue":198395},{"PropertyID":79,"CaseMasterID":452,"PropertyType":"Vehicles","EstimatedValue":378850},{"PropertyID":80,"CaseMasterID":948,"PropertyType":"Documents","EstimatedValue":325315},{"PropertyID":81,"CaseMasterID":758,"PropertyType":"Documents","EstimatedValue":237056},{"PropertyID":82,"CaseMasterID":881,"PropertyType":"Laptop","EstimatedValue":486224},{"PropertyID":83,"CaseMasterID":943,"PropertyType":"Jewellery","EstimatedValue":161428},{"PropertyID":84,"CaseMasterID":554,"PropertyType":"Cash","EstimatedValue":374993},{"PropertyID":85,"CaseMasterID":150,"PropertyType":"Jewellery","EstimatedValue":128243},{"PropertyID":86,"CaseMasterID":791,"PropertyType":"Laptop","EstimatedValue":216388},{"PropertyID":87,"CaseMasterID":144,"PropertyType":"Laptop","EstimatedValue":278131},{"PropertyID":88,"CaseMasterID":59,"PropertyType":"Mobile","EstimatedValue":17593},{"PropertyID":89,"CaseMasterID":195,"PropertyType":"Mobile","EstimatedValue":50676},{"PropertyID":90,"CaseMasterID":688,"PropertyType":"Cash","EstimatedValue":497476},{"PropertyID":91,"CaseMasterID":124,"PropertyType":"Jewellery","EstimatedValue":234777},{"PropertyID":92,"CaseMasterID":92,"PropertyType":"Mobile","EstimatedValue":354045},{"PropertyID":93,"CaseMasterID":274,"PropertyType":"Vehicles","EstimatedValue":372634},{"PropertyID":94,"CaseMasterID":716,"PropertyType":"Laptop","EstimatedValue":496260},{"PropertyID":95,"CaseMasterID":268,"PropertyType":"Laptop","EstimatedValue":244832},{"PropertyID":96,"CaseMasterID":922,"PropertyType":"Documents","EstimatedValue":471664},{"PropertyID":97,"CaseMasterID":532,"PropertyType":"Vehicles","EstimatedValue":156480},{"PropertyID":98,"CaseMasterID":227,"PropertyType":"Jewellery","EstimatedValue":343969},{"PropertyID":99,"CaseMasterID":448,"PropertyType":"Cash","EstimatedValue":12025},{"PropertyID":100,"CaseMasterID":279,"PropertyType":"Laptop","EstimatedValue":462659},{"PropertyID":101,"CaseMasterID":744,"PropertyType":"Laptop","EstimatedValue":358879},{"PropertyID":102,"CaseMasterID":763,"PropertyType":"Vehicles","EstimatedValue":404083},{"PropertyID":103,"CaseMasterID":638,"PropertyType":"Documents","EstimatedValue":456205},{"PropertyID":104,"CaseMasterID":599,"PropertyType":"Laptop","EstimatedValue":103378},{"PropertyID":105,"CaseMasterID":397,"PropertyType":"Vehicles","EstimatedValue":108218},{"PropertyID":106,"CaseMasterID":646,"PropertyType":"Jewellery","EstimatedValue":139545},{"PropertyID":107,"CaseMasterID":299,"PropertyType":"Jewellery","EstimatedValue":434137},{"PropertyID":108,"CaseMasterID":506,"PropertyType":"Mobile","EstimatedValue":174830},{"PropertyID":109,"CaseMasterID":311,"PropertyType":"Jewellery","EstimatedValue":485371},{"PropertyID":110,"CaseMasterID":542,"PropertyType":"Mobile","EstimatedValue":124727},{"PropertyID":111,"CaseMasterID":482,"PropertyType":"Cash","EstimatedValue":291588},{"PropertyID":112,"CaseMasterID":600,"PropertyType":"Vehicles","EstimatedValue":281744},{"PropertyID":113,"CaseMasterID":902,"PropertyType":"Jewellery","EstimatedValue":194857},{"PropertyID":114,"CaseMasterID":401,"PropertyType":"Mobile","EstimatedValue":399428},{"PropertyID":115,"CaseMasterID":230,"PropertyType":"Cash","EstimatedValue":321001},{"PropertyID":116,"CaseMasterID":233,"PropertyType":"Mobile","EstimatedValue":149794},{"PropertyID":117,"CaseMasterID":4,"PropertyType":"Mobile","EstimatedValue":235189},{"PropertyID":118,"CaseMasterID":126,"PropertyType":"Mobile","EstimatedValue":78404},{"PropertyID":119,"CaseMasterID":643,"PropertyType":"Laptop","EstimatedValue":305446},{"PropertyID":120,"CaseMasterID":190,"PropertyType":"Laptop","EstimatedValue":142778},{"PropertyID":121,"CaseMasterID":138,"PropertyType":"Jewellery","EstimatedValue":405130},{"PropertyID":122,"CaseMasterID":448,"PropertyType":"Documents","EstimatedValue":367885},{"PropertyID":123,"CaseMasterID":474,"PropertyType":"Documents","EstimatedValue":492587},{"PropertyID":124,"CaseMasterID":296,"PropertyType":"Cash","EstimatedValue":176638},{"PropertyID":125,"CaseMasterID":683,"PropertyType":"Jewellery","EstimatedValue":408086},{"PropertyID":126,"CaseMasterID":767,"PropertyType":"Documents","EstimatedValue":444813},{"PropertyID":127,"CaseMasterID":487,"PropertyType":"Vehicles","EstimatedValue":154224},{"PropertyID":128,"CaseMasterID":643,"PropertyType":"Jewellery","EstimatedValue":434913},{"PropertyID":129,"CaseMasterID":199,"PropertyType":"Vehicles","EstimatedValue":138882},{"PropertyID":130,"CaseMasterID":876,"PropertyType":"Jewellery","EstimatedValue":423987},{"PropertyID":131,"CaseMasterID":853,"PropertyType":"Vehicles","EstimatedValue":44151},{"PropertyID":132,"CaseMasterID":967,"PropertyType":"Documents","EstimatedValue":8861},{"PropertyID":133,"CaseMasterID":286,"PropertyType":"Mobile","EstimatedValue":496686},{"PropertyID":134,"CaseMasterID":952,"PropertyType":"Jewellery","EstimatedValue":50354},{"PropertyID":135,"CaseMasterID":796,"PropertyType":"Cash","EstimatedValue":359211},{"PropertyID":136,"CaseMasterID":364,"PropertyType":"Documents","EstimatedValue":93366},{"PropertyID":137,"CaseMasterID":430,"PropertyType":"Vehicles","EstimatedValue":270802},{"PropertyID":138,"CaseMasterID":398,"PropertyType":"Jewellery","EstimatedValue":209200},{"PropertyID":139,"CaseMasterID":864,"PropertyType":"Documents","EstimatedValue":273220},{"PropertyID":140,"CaseMasterID":689,"PropertyType":"Laptop","EstimatedValue":454007},{"PropertyID":141,"CaseMasterID":997,"PropertyType":"Laptop","EstimatedValue":382738},{"PropertyID":142,"CaseMasterID":983,"PropertyType":"Vehicles","EstimatedValue":63152},{"PropertyID":143,"CaseMasterID":339,"PropertyType":"Mobile","EstimatedValue":80953},{"PropertyID":144,"CaseMasterID":945,"PropertyType":"Laptop","EstimatedValue":438558},{"PropertyID":145,"CaseMasterID":510,"PropertyType":"Mobile","EstimatedValue":392198},{"PropertyID":146,"CaseMasterID":998,"PropertyType":"Documents","EstimatedValue":329017},{"PropertyID":147,"CaseMasterID":906,"PropertyType":"Cash","EstimatedValue":447134},{"PropertyID":148,"CaseMasterID":438,"PropertyType":"Vehicles","EstimatedValue":498993},{"PropertyID":149,"CaseMasterID":175,"PropertyType":"Cash","EstimatedValue":151689},{"PropertyID":150,"CaseMasterID":460,"PropertyType":"Vehicles","EstimatedValue":324176},{"PropertyID":151,"CaseMasterID":8,"PropertyType":"Vehicles","EstimatedValue":485916},{"PropertyID":152,"CaseMasterID":423,"PropertyType":"Vehicles","EstimatedValue":357030},{"PropertyID":153,"CaseMasterID":984,"PropertyType":"Mobile","EstimatedValue":219723},{"PropertyID":154,"CaseMasterID":357,"PropertyType":"Vehicles","EstimatedValue":356021},{"PropertyID":155,"CaseMasterID":416,"PropertyType":"Documents","EstimatedValue":259220},{"PropertyID":156,"CaseMasterID":92,"PropertyType":"Vehicles","EstimatedValue":184791},{"PropertyID":157,"CaseMasterID":310,"PropertyType":"Mobile","EstimatedValue":162291},{"PropertyID":158,"CaseMasterID":224,"PropertyType":"Jewellery","EstimatedValue":292412},{"PropertyID":159,"CaseMasterID":500,"PropertyType":"Vehicles","EstimatedValue":313965},{"PropertyID":160,"CaseMasterID":374,"PropertyType":"Jewellery","EstimatedValue":40543},{"PropertyID":161,"CaseMasterID":731,"PropertyType":"Vehicles","EstimatedValue":90205},{"PropertyID":162,"CaseMasterID":240,"PropertyType":"Mobile","EstimatedValue":178146},{"PropertyID":163,"CaseMasterID":198,"PropertyType":"Cash","EstimatedValue":213048},{"PropertyID":164,"CaseMasterID":236,"PropertyType":"Jewellery","EstimatedValue":207967},{"PropertyID":165,"CaseMasterID":298,"PropertyType":"Laptop","EstimatedValue":161606},{"PropertyID":166,"CaseMasterID":734,"PropertyType":"Vehicles","EstimatedValue":101826},{"PropertyID":167,"CaseMasterID":978,"PropertyType":"Jewellery","EstimatedValue":446500},{"PropertyID":168,"CaseMasterID":312,"PropertyType":"Jewellery","EstimatedValue":101171},{"PropertyID":169,"CaseMasterID":223,"PropertyType":"Jewellery","EstimatedValue":294207},{"PropertyID":170,"CaseMasterID":436,"PropertyType":"Cash","EstimatedValue":272778},{"PropertyID":171,"CaseMasterID":517,"PropertyType":"Documents","EstimatedValue":483692},{"PropertyID":172,"CaseMasterID":289,"PropertyType":"Cash","EstimatedValue":131285},{"PropertyID":173,"CaseMasterID":322,"PropertyType":"Mobile","EstimatedValue":61270},{"PropertyID":174,"CaseMasterID":940,"PropertyType":"Jewellery","EstimatedValue":376657},{"PropertyID":175,"CaseMasterID":977,"PropertyType":"Cash","EstimatedValue":266524},{"PropertyID":176,"CaseMasterID":726,"PropertyType":"Laptop","EstimatedValue":438301},{"PropertyID":177,"CaseMasterID":238,"PropertyType":"Documents","EstimatedValue":44107},{"PropertyID":178,"CaseMasterID":416,"PropertyType":"Documents","EstimatedValue":397147},{"PropertyID":179,"CaseMasterID":239,"PropertyType":"Vehicles","EstimatedValue":359252},{"PropertyID":180,"CaseMasterID":791,"PropertyType":"Cash","EstimatedValue":318928},{"PropertyID":181,"CaseMasterID":45,"PropertyType":"Laptop","EstimatedValue":68583},{"PropertyID":182,"CaseMasterID":42,"PropertyType":"Documents","EstimatedValue":355294},{"PropertyID":183,"CaseMasterID":802,"PropertyType":"Laptop","EstimatedValue":287489},{"PropertyID":184,"CaseMasterID":82,"PropertyType":"Mobile","EstimatedValue":45591},{"PropertyID":185,"CaseMasterID":312,"PropertyType":"Cash","EstimatedValue":476385},{"PropertyID":186,"CaseMasterID":846,"PropertyType":"Cash","EstimatedValue":423892},{"PropertyID":187,"CaseMasterID":335,"PropertyType":"Vehicles","EstimatedValue":73436},{"PropertyID":188,"CaseMasterID":188,"PropertyType":"Laptop","EstimatedValue":30897},{"PropertyID":189,"CaseMasterID":531,"PropertyType":"Jewellery","EstimatedValue":297293},{"PropertyID":190,"CaseMasterID":954,"PropertyType":"Vehicles","EstimatedValue":482235},{"PropertyID":191,"CaseMasterID":970,"PropertyType":"Laptop","EstimatedValue":229224},{"PropertyID":192,"CaseMasterID":25,"PropertyType":"Laptop","EstimatedValue":364768},{"PropertyID":193,"CaseMasterID":637,"PropertyType":"Cash","EstimatedValue":336469},{"PropertyID":194,"CaseMasterID":94,"PropertyType":"Mobile","EstimatedValue":107621},{"PropertyID":195,"CaseMasterID":543,"PropertyType":"Laptop","EstimatedValue":48277},{"PropertyID":196,"CaseMasterID":180,"PropertyType":"Laptop","EstimatedValue":148396},{"PropertyID":197,"CaseMasterID":806,"PropertyType":"Documents","EstimatedValue":131794},{"PropertyID":198,"CaseMasterID":158,"PropertyType":"Documents","EstimatedValue":94576},{"PropertyID":199,"CaseMasterID":873,"PropertyType":"Jewellery","EstimatedValue":210205},{"PropertyID":200,"CaseMasterID":229,"PropertyType":"Jewellery","EstimatedValue":217909},{"PropertyID":201,"CaseMasterID":670,"PropertyType":"Laptop","EstimatedValue":230842},{"PropertyID":202,"CaseMasterID":340,"PropertyType":"Laptop","EstimatedValue":449216},{"PropertyID":203,"CaseMasterID":386,"PropertyType":"Cash","EstimatedValue":96336},{"PropertyID":204,"CaseMasterID":766,"PropertyType":"Documents","EstimatedValue":97135},{"PropertyID":205,"CaseMasterID":874,"PropertyType":"Jewellery","EstimatedValue":86123},{"PropertyID":206,"CaseMasterID":530,"PropertyType":"Vehicles","EstimatedValue":83850},{"PropertyID":207,"CaseMasterID":412,"PropertyType":"Jewellery","EstimatedValue":309301},{"PropertyID":208,"CaseMasterID":177,"PropertyType":"Laptop","EstimatedValue":236907},{"PropertyID":209,"CaseMasterID":58,"PropertyType":"Mobile","EstimatedValue":184713},{"PropertyID":210,"CaseMasterID":178,"PropertyType":"Cash","EstimatedValue":312331},{"PropertyID":211,"CaseMasterID":224,"PropertyType":"Laptop","EstimatedValue":349558},{"PropertyID":212,"CaseMasterID":878,"PropertyType":"Documents","EstimatedValue":6633},{"PropertyID":213,"CaseMasterID":587,"PropertyType":"Mobile","EstimatedValue":490178},{"PropertyID":214,"CaseMasterID":780,"PropertyType":"Mobile","EstimatedValue":185430},{"PropertyID":215,"CaseMasterID":406,"PropertyType":"Cash","EstimatedValue":98598},{"PropertyID":216,"CaseMasterID":392,"PropertyType":"Laptop","EstimatedValue":282322},{"PropertyID":217,"CaseMasterID":587,"PropertyType":"Jewellery","EstimatedValue":223879},{"PropertyID":218,"CaseMasterID":502,"PropertyType":"Cash","EstimatedValue":264585},{"PropertyID":219,"CaseMasterID":300,"PropertyType":"Cash","EstimatedValue":17809},{"PropertyID":220,"CaseMasterID":671,"PropertyType":"Cash","EstimatedValue":118791},{"PropertyID":221,"CaseMasterID":954,"PropertyType":"Vehicles","EstimatedValue":330037},{"PropertyID":222,"CaseMasterID":740,"PropertyType":"Cash","EstimatedValue":301647},{"PropertyID":223,"CaseMasterID":851,"PropertyType":"Vehicles","EstimatedValue":73710},{"PropertyID":224,"CaseMasterID":314,"PropertyType":"Vehicles","EstimatedValue":19164},{"PropertyID":225,"CaseMasterID":885,"PropertyType":"Cash","EstimatedValue":491187},{"PropertyID":226,"CaseMasterID":278,"PropertyType":"Jewellery","EstimatedValue":128651},{"PropertyID":227,"CaseMasterID":132,"PropertyType":"Documents","EstimatedValue":95687},{"PropertyID":228,"CaseMasterID":384,"PropertyType":"Mobile","EstimatedValue":147227},{"PropertyID":229,"CaseMasterID":325,"PropertyType":"Jewellery","EstimatedValue":246850},{"PropertyID":230,"CaseMasterID":142,"PropertyType":"Mobile","EstimatedValue":460380},{"PropertyID":231,"CaseMasterID":162,"PropertyType":"Jewellery","EstimatedValue":96652},{"PropertyID":232,"CaseMasterID":135,"PropertyType":"Vehicles","EstimatedValue":6167},{"PropertyID":233,"CaseMasterID":44,"PropertyType":"Cash","EstimatedValue":224520},{"PropertyID":234,"CaseMasterID":994,"PropertyType":"Vehicles","EstimatedValue":219042},{"PropertyID":235,"CaseMasterID":35,"PropertyType":"Mobile","EstimatedValue":376874},{"PropertyID":236,"CaseMasterID":15,"PropertyType":"Jewellery","EstimatedValue":131963},{"PropertyID":237,"CaseMasterID":616,"PropertyType":"Jewellery","EstimatedValue":31534},{"PropertyID":238,"CaseMasterID":626,"PropertyType":"Vehicles","EstimatedValue":349936},{"PropertyID":239,"CaseMasterID":814,"PropertyType":"Mobile","EstimatedValue":177611},{"PropertyID":240,"CaseMasterID":116,"PropertyType":"Jewellery","EstimatedValue":85788},{"PropertyID":241,"CaseMasterID":899,"PropertyType":"Documents","EstimatedValue":140758},{"PropertyID":242,"CaseMasterID":499,"PropertyType":"Laptop","EstimatedValue":476892},{"PropertyID":243,"CaseMasterID":917,"PropertyType":"Mobile","EstimatedValue":266093},{"PropertyID":244,"CaseMasterID":834,"PropertyType":"Documents","EstimatedValue":468767},{"PropertyID":245,"CaseMasterID":468,"PropertyType":"Vehicles","EstimatedValue":349791},{"PropertyID":246,"CaseMasterID":649,"PropertyType":"Mobile","EstimatedValue":60899},{"PropertyID":247,"CaseMasterID":369,"PropertyType":"Documents","EstimatedValue":232734},{"PropertyID":248,"CaseMasterID":478,"PropertyType":"Laptop","EstimatedValue":452118},{"PropertyID":249,"CaseMasterID":229,"PropertyType":"Mobile","EstimatedValue":332467},{"PropertyID":250,"CaseMasterID":734,"PropertyType":"Jewellery","EstimatedValue":68562},{"PropertyID":251,"CaseMasterID":637,"PropertyType":"Jewellery","EstimatedValue":336269},{"PropertyID":252,"CaseMasterID":606,"PropertyType":"Laptop","EstimatedValue":480059},{"PropertyID":253,"CaseMasterID":120,"PropertyType":"Jewellery","EstimatedValue":286295},{"PropertyID":254,"CaseMasterID":495,"PropertyType":"Laptop","EstimatedValue":99644},{"PropertyID":255,"CaseMasterID":806,"PropertyType":"Mobile","EstimatedValue":62890},{"PropertyID":256,"CaseMasterID":886,"PropertyType":"Documents","EstimatedValue":365482},{"PropertyID":257,"CaseMasterID":455,"PropertyType":"Cash","EstimatedValue":387659},{"PropertyID":258,"CaseMasterID":348,"PropertyType":"Laptop","EstimatedValue":347157},{"PropertyID":259,"CaseMasterID":583,"PropertyType":"Laptop","EstimatedValue":380137},{"PropertyID":260,"CaseMasterID":559,"PropertyType":"Documents","EstimatedValue":134154},{"PropertyID":261,"CaseMasterID":838,"PropertyType":"Jewellery","EstimatedValue":419542},{"PropertyID":262,"CaseMasterID":366,"PropertyType":"Documents","EstimatedValue":123289},{"PropertyID":263,"CaseMasterID":179,"PropertyType":"Mobile","EstimatedValue":445759},{"PropertyID":264,"CaseMasterID":837,"PropertyType":"Documents","EstimatedValue":438656},{"PropertyID":265,"CaseMasterID":186,"PropertyType":"Documents","EstimatedValue":444974},{"PropertyID":266,"CaseMasterID":397,"PropertyType":"Documents","EstimatedValue":264420},{"PropertyID":267,"CaseMasterID":359,"PropertyType":"Documents","EstimatedValue":67554},{"PropertyID":268,"CaseMasterID":134,"PropertyType":"Documents","EstimatedValue":483474},{"PropertyID":269,"CaseMasterID":902,"PropertyType":"Mobile","EstimatedValue":53268},{"PropertyID":270,"CaseMasterID":568,"PropertyType":"Cash","EstimatedValue":162789},{"PropertyID":271,"CaseMasterID":588,"PropertyType":"Jewellery","EstimatedValue":341059},{"PropertyID":272,"CaseMasterID":714,"PropertyType":"Documents","EstimatedValue":330685},{"PropertyID":273,"CaseMasterID":204,"PropertyType":"Laptop","EstimatedValue":340906},{"PropertyID":274,"CaseMasterID":675,"PropertyType":"Documents","EstimatedValue":236001},{"PropertyID":275,"CaseMasterID":195,"PropertyType":"Jewellery","EstimatedValue":385426},{"PropertyID":276,"CaseMasterID":720,"PropertyType":"Vehicles","EstimatedValue":66692},{"PropertyID":277,"CaseMasterID":443,"PropertyType":"Jewellery","EstimatedValue":132012},{"PropertyID":278,"CaseMasterID":508,"PropertyType":"Laptop","EstimatedValue":338808},{"PropertyID":279,"CaseMasterID":153,"PropertyType":"Jewellery","EstimatedValue":135276},{"PropertyID":280,"CaseMasterID":422,"PropertyType":"Vehicles","EstimatedValue":317053},{"PropertyID":281,"CaseMasterID":341,"PropertyType":"Documents","EstimatedValue":179603},{"PropertyID":282,"CaseMasterID":609,"PropertyType":"Documents","EstimatedValue":318578},{"PropertyID":283,"CaseMasterID":231,"PropertyType":"Mobile","EstimatedValue":404057},{"PropertyID":284,"CaseMasterID":291,"PropertyType":"Vehicles","EstimatedValue":134693},{"PropertyID":285,"CaseMasterID":470,"PropertyType":"Documents","EstimatedValue":486423},{"PropertyID":286,"CaseMasterID":435,"PropertyType":"Documents","EstimatedValue":441045},{"PropertyID":287,"CaseMasterID":685,"PropertyType":"Laptop","EstimatedValue":25046},{"PropertyID":288,"CaseMasterID":942,"PropertyType":"Cash","EstimatedValue":190554},{"PropertyID":289,"CaseMasterID":765,"PropertyType":"Laptop","EstimatedValue":93745},{"PropertyID":290,"CaseMasterID":157,"PropertyType":"Vehicles","EstimatedValue":156528},{"PropertyID":291,"CaseMasterID":583,"PropertyType":"Vehicles","EstimatedValue":227347},{"PropertyID":292,"CaseMasterID":727,"PropertyType":"Vehicles","EstimatedValue":298785},{"PropertyID":293,"CaseMasterID":744,"PropertyType":"Documents","EstimatedValue":425361},{"PropertyID":294,"CaseMasterID":390,"PropertyType":"Laptop","EstimatedValue":54852},{"PropertyID":295,"CaseMasterID":328,"PropertyType":"Jewellery","EstimatedValue":210513},{"PropertyID":296,"CaseMasterID":978,"PropertyType":"Laptop","EstimatedValue":380025},{"PropertyID":297,"CaseMasterID":352,"PropertyType":"Documents","EstimatedValue":494792},{"PropertyID":298,"CaseMasterID":384,"PropertyType":"Vehicles","EstimatedValue":450223},{"PropertyID":299,"CaseMasterID":26,"PropertyType":"Vehicles","EstimatedValue":312811},{"PropertyID":300,"CaseMasterID":178,"PropertyType":"Cash","EstimatedValue":273506},{"PropertyID":301,"CaseMasterID":817,"PropertyType":"Vehicles","EstimatedValue":76137},{"PropertyID":302,"CaseMasterID":989,"PropertyType":"Mobile","EstimatedValue":499616},{"PropertyID":303,"CaseMasterID":313,"PropertyType":"Laptop","EstimatedValue":409815},{"PropertyID":304,"CaseMasterID":212,"PropertyType":"Laptop","EstimatedValue":139092},{"PropertyID":305,"CaseMasterID":572,"PropertyType":"Documents","EstimatedValue":473222},{"PropertyID":306,"CaseMasterID":24,"PropertyType":"Vehicles","EstimatedValue":439121},{"PropertyID":307,"CaseMasterID":504,"PropertyType":"Laptop","EstimatedValue":365256},{"PropertyID":308,"CaseMasterID":846,"PropertyType":"Documents","EstimatedValue":3633},{"PropertyID":309,"CaseMasterID":274,"PropertyType":"Vehicles","EstimatedValue":306170},{"PropertyID":310,"CaseMasterID":804,"PropertyType":"Documents","EstimatedValue":126571},{"PropertyID":311,"CaseMasterID":235,"PropertyType":"Documents","EstimatedValue":336353},{"PropertyID":312,"CaseMasterID":323,"PropertyType":"Laptop","EstimatedValue":419933},{"PropertyID":313,"CaseMasterID":230,"PropertyType":"Laptop","EstimatedValue":167386},{"PropertyID":314,"CaseMasterID":901,"PropertyType":"Jewellery","EstimatedValue":195697},{"PropertyID":315,"CaseMasterID":418,"PropertyType":"Documents","EstimatedValue":246734},{"PropertyID":316,"CaseMasterID":476,"PropertyType":"Mobile","EstimatedValue":451774},{"PropertyID":317,"CaseMasterID":293,"PropertyType":"Laptop","EstimatedValue":91888},{"PropertyID":318,"CaseMasterID":170,"PropertyType":"Jewellery","EstimatedValue":152673},{"PropertyID":319,"CaseMasterID":610,"PropertyType":"Mobile","EstimatedValue":377011},{"PropertyID":320,"CaseMasterID":771,"PropertyType":"Jewellery","EstimatedValue":272091},{"PropertyID":321,"CaseMasterID":455,"PropertyType":"Cash","EstimatedValue":490677},{"PropertyID":322,"CaseMasterID":189,"PropertyType":"Vehicles","EstimatedValue":160703},{"PropertyID":323,"CaseMasterID":500,"PropertyType":"Vehicles","EstimatedValue":161230},{"PropertyID":324,"CaseMasterID":92,"PropertyType":"Vehicles","EstimatedValue":284086},{"PropertyID":325,"CaseMasterID":638,"PropertyType":"Vehicles","EstimatedValue":229344},{"PropertyID":326,"CaseMasterID":64,"PropertyType":"Laptop","EstimatedValue":9963},{"PropertyID":327,"CaseMasterID":530,"PropertyType":"Mobile","EstimatedValue":161738},{"PropertyID":328,"CaseMasterID":950,"PropertyType":"Jewellery","EstimatedValue":157180},{"PropertyID":329,"CaseMasterID":814,"PropertyType":"Vehicles","EstimatedValue":112344},{"PropertyID":330,"CaseMasterID":718,"PropertyType":"Mobile","EstimatedValue":29302},{"PropertyID":331,"CaseMasterID":182,"PropertyType":"Mobile","EstimatedValue":293821},{"PropertyID":332,"CaseMasterID":234,"PropertyType":"Laptop","EstimatedValue":496059},{"PropertyID":333,"CaseMasterID":459,"PropertyType":"Vehicles","EstimatedValue":391073},{"PropertyID":334,"CaseMasterID":892,"PropertyType":"Jewellery","EstimatedValue":64049},{"PropertyID":335,"CaseMasterID":983,"PropertyType":"Vehicles","EstimatedValue":163073},{"PropertyID":336,"CaseMasterID":855,"PropertyType":"Cash","EstimatedValue":141516},{"PropertyID":337,"CaseMasterID":184,"PropertyType":"Documents","EstimatedValue":338192},{"PropertyID":338,"CaseMasterID":870,"PropertyType":"Vehicles","EstimatedValue":407913},{"PropertyID":339,"CaseMasterID":66,"PropertyType":"Vehicles","EstimatedValue":462954},{"PropertyID":340,"CaseMasterID":153,"PropertyType":"Documents","EstimatedValue":280591},{"PropertyID":341,"CaseMasterID":872,"PropertyType":"Jewellery","EstimatedValue":484335},{"PropertyID":342,"CaseMasterID":819,"PropertyType":"Laptop","EstimatedValue":26641},{"PropertyID":343,"CaseMasterID":451,"PropertyType":"Jewellery","EstimatedValue":360465},{"PropertyID":344,"CaseMasterID":358,"PropertyType":"Laptop","EstimatedValue":279677},{"PropertyID":345,"CaseMasterID":783,"PropertyType":"Jewellery","EstimatedValue":83505},{"PropertyID":346,"CaseMasterID":66,"PropertyType":"Documents","EstimatedValue":125057},{"PropertyID":347,"CaseMasterID":846,"PropertyType":"Jewellery","EstimatedValue":350107},{"PropertyID":348,"CaseMasterID":342,"PropertyType":"Cash","EstimatedValue":448329},{"PropertyID":349,"CaseMasterID":261,"PropertyType":"Documents","EstimatedValue":418957},{"PropertyID":350,"CaseMasterID":916,"PropertyType":"Vehicles","EstimatedValue":109791},{"PropertyID":351,"CaseMasterID":746,"PropertyType":"Vehicles","EstimatedValue":144889},{"PropertyID":352,"CaseMasterID":229,"PropertyType":"Cash","EstimatedValue":194807},{"PropertyID":353,"CaseMasterID":7,"PropertyType":"Mobile","EstimatedValue":43740},{"PropertyID":354,"CaseMasterID":459,"PropertyType":"Jewellery","EstimatedValue":467391},{"PropertyID":355,"CaseMasterID":254,"PropertyType":"Laptop","EstimatedValue":354132},{"PropertyID":356,"CaseMasterID":18,"PropertyType":"Laptop","EstimatedValue":201991},{"PropertyID":357,"CaseMasterID":483,"PropertyType":"Laptop","EstimatedValue":174757},{"PropertyID":358,"CaseMasterID":133,"PropertyType":"Vehicles","EstimatedValue":329271},{"PropertyID":359,"CaseMasterID":522,"PropertyType":"Documents","EstimatedValue":149897},{"PropertyID":360,"CaseMasterID":767,"PropertyType":"Vehicles","EstimatedValue":102265},{"PropertyID":361,"CaseMasterID":338,"PropertyType":"Mobile","EstimatedValue":286412},{"PropertyID":362,"CaseMasterID":522,"PropertyType":"Vehicles","EstimatedValue":183999},{"PropertyID":363,"CaseMasterID":100,"PropertyType":"Documents","EstimatedValue":313961},{"PropertyID":364,"CaseMasterID":796,"PropertyType":"Vehicles","EstimatedValue":440006},{"PropertyID":365,"CaseMasterID":273,"PropertyType":"Cash","EstimatedValue":82767},{"PropertyID":366,"CaseMasterID":186,"PropertyType":"Jewellery","EstimatedValue":239884},{"PropertyID":367,"CaseMasterID":765,"PropertyType":"Jewellery","EstimatedValue":164026},{"PropertyID":368,"CaseMasterID":173,"PropertyType":"Laptop","EstimatedValue":425894},{"PropertyID":369,"CaseMasterID":699,"PropertyType":"Documents","EstimatedValue":58230},{"PropertyID":370,"CaseMasterID":217,"PropertyType":"Vehicles","EstimatedValue":479113},{"PropertyID":371,"CaseMasterID":162,"PropertyType":"Cash","EstimatedValue":480342},{"PropertyID":372,"CaseMasterID":968,"PropertyType":"Documents","EstimatedValue":262033},{"PropertyID":373,"CaseMasterID":723,"PropertyType":"Vehicles","EstimatedValue":252311},{"PropertyID":374,"CaseMasterID":955,"PropertyType":"Vehicles","EstimatedValue":368683},{"PropertyID":375,"CaseMasterID":247,"PropertyType":"Documents","EstimatedValue":414831},{"PropertyID":376,"CaseMasterID":165,"PropertyType":"Mobile","EstimatedValue":93871},{"PropertyID":377,"CaseMasterID":344,"PropertyType":"Vehicles","EstimatedValue":212350},{"PropertyID":378,"CaseMasterID":334,"PropertyType":"Laptop","EstimatedValue":487647},{"PropertyID":379,"CaseMasterID":300,"PropertyType":"Documents","EstimatedValue":399352},{"PropertyID":380,"CaseMasterID":631,"PropertyType":"Mobile","EstimatedValue":120746},{"PropertyID":381,"CaseMasterID":956,"PropertyType":"Mobile","EstimatedValue":196188},{"PropertyID":382,"CaseMasterID":268,"PropertyType":"Jewellery","EstimatedValue":473645},{"PropertyID":383,"CaseMasterID":160,"PropertyType":"Laptop","EstimatedValue":276306},{"PropertyID":384,"CaseMasterID":609,"PropertyType":"Jewellery","EstimatedValue":422711},{"PropertyID":385,"CaseMasterID":709,"PropertyType":"Mobile","EstimatedValue":331615},{"PropertyID":386,"CaseMasterID":720,"PropertyType":"Documents","EstimatedValue":398956},{"PropertyID":387,"CaseMasterID":575,"PropertyType":"Cash","EstimatedValue":279811},{"PropertyID":388,"CaseMasterID":659,"PropertyType":"Mobile","EstimatedValue":134431},{"PropertyID":389,"CaseMasterID":467,"PropertyType":"Cash","EstimatedValue":305855},{"PropertyID":390,"CaseMasterID":370,"PropertyType":"Mobile","EstimatedValue":26003},{"PropertyID":391,"CaseMasterID":147,"PropertyType":"Mobile","EstimatedValue":235619},{"PropertyID":392,"CaseMasterID":927,"PropertyType":"Cash","EstimatedValue":25799},{"PropertyID":393,"CaseMasterID":330,"PropertyType":"Laptop","EstimatedValue":185110},{"PropertyID":394,"CaseMasterID":953,"PropertyType":"Jewellery","EstimatedValue":48446},{"PropertyID":395,"CaseMasterID":131,"PropertyType":"Jewellery","EstimatedValue":414009},{"PropertyID":396,"CaseMasterID":363,"PropertyType":"Laptop","EstimatedValue":75050},{"PropertyID":397,"CaseMasterID":559,"PropertyType":"Laptop","EstimatedValue":90785},{"PropertyID":398,"CaseMasterID":196,"PropertyType":"Jewellery","EstimatedValue":113057},{"PropertyID":399,"CaseMasterID":461,"PropertyType":"Mobile","EstimatedValue":172089},{"PropertyID":400,"CaseMasterID":700,"PropertyType":"Laptop","EstimatedValue":187921},{"PropertyID":401,"CaseMasterID":298,"PropertyType":"Laptop","EstimatedValue":277088},{"PropertyID":402,"CaseMasterID":913,"PropertyType":"Jewellery","EstimatedValue":160555},{"PropertyID":403,"CaseMasterID":743,"PropertyType":"Mobile","EstimatedValue":75928},{"PropertyID":404,"CaseMasterID":105,"PropertyType":"Jewellery","EstimatedValue":358117},{"PropertyID":405,"CaseMasterID":353,"PropertyType":"Laptop","EstimatedValue":139752},{"PropertyID":406,"CaseMasterID":782,"PropertyType":"Vehicles","EstimatedValue":183473},{"PropertyID":407,"CaseMasterID":533,"PropertyType":"Vehicles","EstimatedValue":461915},{"PropertyID":408,"CaseMasterID":418,"PropertyType":"Vehicles","EstimatedValue":346094},{"PropertyID":409,"CaseMasterID":914,"PropertyType":"Jewellery","EstimatedValue":437132},{"PropertyID":410,"CaseMasterID":554,"PropertyType":"Jewellery","EstimatedValue":445873},{"PropertyID":411,"CaseMasterID":604,"PropertyType":"Cash","EstimatedValue":91832},{"PropertyID":412,"CaseMasterID":752,"PropertyType":"Jewellery","EstimatedValue":440547},{"PropertyID":413,"CaseMasterID":183,"PropertyType":"Cash","EstimatedValue":353664},{"PropertyID":414,"CaseMasterID":647,"PropertyType":"Vehicles","EstimatedValue":378050},{"PropertyID":415,"CaseMasterID":588,"PropertyType":"Cash","EstimatedValue":104678},{"PropertyID":416,"CaseMasterID":917,"PropertyType":"Cash","EstimatedValue":186110},{"PropertyID":417,"CaseMasterID":251,"PropertyType":"Laptop","EstimatedValue":177295},{"PropertyID":418,"CaseMasterID":884,"PropertyType":"Laptop","EstimatedValue":164188},{"PropertyID":419,"CaseMasterID":285,"PropertyType":"Vehicles","EstimatedValue":256019},{"PropertyID":420,"CaseMasterID":492,"PropertyType":"Cash","EstimatedValue":445481},{"PropertyID":421,"CaseMasterID":563,"PropertyType":"Mobile","EstimatedValue":334782},{"PropertyID":422,"CaseMasterID":918,"PropertyType":"Vehicles","EstimatedValue":166927},{"PropertyID":423,"CaseMasterID":113,"PropertyType":"Cash","EstimatedValue":316976},{"PropertyID":424,"CaseMasterID":792,"PropertyType":"Cash","EstimatedValue":339879},{"PropertyID":425,"CaseMasterID":220,"PropertyType":"Vehicles","EstimatedValue":465756},{"PropertyID":426,"CaseMasterID":731,"PropertyType":"Documents","EstimatedValue":390062},{"PropertyID":427,"CaseMasterID":269,"PropertyType":"Documents","EstimatedValue":213423},{"PropertyID":428,"CaseMasterID":952,"PropertyType":"Laptop","EstimatedValue":153531},{"PropertyID":429,"CaseMasterID":206,"PropertyType":"Vehicles","EstimatedValue":102787},{"PropertyID":430,"CaseMasterID":163,"PropertyType":"Vehicles","EstimatedValue":443173},{"PropertyID":431,"CaseMasterID":402,"PropertyType":"Jewellery","EstimatedValue":138554},{"PropertyID":432,"CaseMasterID":289,"PropertyType":"Vehicles","EstimatedValue":365089},{"PropertyID":433,"CaseMasterID":284,"PropertyType":"Vehicles","EstimatedValue":225086},{"PropertyID":434,"CaseMasterID":575,"PropertyType":"Documents","EstimatedValue":292902},{"PropertyID":435,"CaseMasterID":440,"PropertyType":"Jewellery","EstimatedValue":220516},{"PropertyID":436,"CaseMasterID":918,"PropertyType":"Vehicles","EstimatedValue":34864},{"PropertyID":437,"CaseMasterID":841,"PropertyType":"Cash","EstimatedValue":142367},{"PropertyID":438,"CaseMasterID":450,"PropertyType":"Cash","EstimatedValue":39516},{"PropertyID":439,"CaseMasterID":496,"PropertyType":"Documents","EstimatedValue":346342},{"PropertyID":440,"CaseMasterID":145,"PropertyType":"Cash","EstimatedValue":299682},{"PropertyID":441,"CaseMasterID":132,"PropertyType":"Cash","EstimatedValue":490910},{"PropertyID":442,"CaseMasterID":205,"PropertyType":"Vehicles","EstimatedValue":268966},{"PropertyID":443,"CaseMasterID":243,"PropertyType":"Documents","EstimatedValue":29504},{"PropertyID":444,"CaseMasterID":69,"PropertyType":"Mobile","EstimatedValue":212072},{"PropertyID":445,"CaseMasterID":471,"PropertyType":"Documents","EstimatedValue":10816},{"PropertyID":446,"CaseMasterID":243,"PropertyType":"Laptop","EstimatedValue":118055},{"PropertyID":447,"CaseMasterID":48,"PropertyType":"Cash","EstimatedValue":21642},{"PropertyID":448,"CaseMasterID":464,"PropertyType":"Laptop","EstimatedValue":484335},{"PropertyID":449,"CaseMasterID":242,"PropertyType":"Laptop","EstimatedValue":309677},{"PropertyID":450,"CaseMasterID":22,"PropertyType":"Mobile","EstimatedValue":254920},{"PropertyID":451,"CaseMasterID":641,"PropertyType":"Documents","EstimatedValue":491308},{"PropertyID":452,"CaseMasterID":442,"PropertyType":"Laptop","EstimatedValue":42255},{"PropertyID":453,"CaseMasterID":853,"PropertyType":"Vehicles","EstimatedValue":331536},{"PropertyID":454,"CaseMasterID":983,"PropertyType":"Cash","EstimatedValue":154696},{"PropertyID":455,"CaseMasterID":959,"PropertyType":"Jewellery","EstimatedValue":88694},{"PropertyID":456,"CaseMasterID":500,"PropertyType":"Laptop","EstimatedValue":177866},{"PropertyID":457,"CaseMasterID":546,"PropertyType":"Documents","EstimatedValue":182281},{"PropertyID":458,"CaseMasterID":900,"PropertyType":"Cash","EstimatedValue":319001},{"PropertyID":459,"CaseMasterID":252,"PropertyType":"Laptop","EstimatedValue":99666},{"PropertyID":460,"CaseMasterID":58,"PropertyType":"Documents","EstimatedValue":296973},{"PropertyID":461,"CaseMasterID":431,"PropertyType":"Vehicles","EstimatedValue":475791},{"PropertyID":462,"CaseMasterID":170,"PropertyType":"Documents","EstimatedValue":424962},{"PropertyID":463,"CaseMasterID":707,"PropertyType":"Jewellery","EstimatedValue":407423},{"PropertyID":464,"CaseMasterID":797,"PropertyType":"Jewellery","EstimatedValue":469372},{"PropertyID":465,"CaseMasterID":772,"PropertyType":"Jewellery","EstimatedValue":340054},{"PropertyID":466,"CaseMasterID":134,"PropertyType":"Laptop","EstimatedValue":471654},{"PropertyID":467,"CaseMasterID":346,"PropertyType":"Jewellery","EstimatedValue":290556},{"PropertyID":468,"CaseMasterID":12,"PropertyType":"Mobile","EstimatedValue":397296},{"PropertyID":469,"CaseMasterID":395,"PropertyType":"Jewellery","EstimatedValue":99173},{"PropertyID":470,"CaseMasterID":96,"PropertyType":"Documents","EstimatedValue":325408},{"PropertyID":471,"CaseMasterID":179,"PropertyType":"Mobile","EstimatedValue":223689},{"PropertyID":472,"CaseMasterID":451,"PropertyType":"Cash","EstimatedValue":5606},{"PropertyID":473,"CaseMasterID":226,"PropertyType":"Vehicles","EstimatedValue":67993},{"PropertyID":474,"CaseMasterID":405,"PropertyType":"Mobile","EstimatedValue":152196},{"PropertyID":475,"CaseMasterID":280,"PropertyType":"Jewellery","EstimatedValue":273659},{"PropertyID":476,"CaseMasterID":149,"PropertyType":"Mobile","EstimatedValue":274793},{"PropertyID":477,"CaseMasterID":65,"PropertyType":"Laptop","EstimatedValue":176752},{"PropertyID":478,"CaseMasterID":90,"PropertyType":"Cash","EstimatedValue":470364},{"PropertyID":479,"CaseMasterID":146,"PropertyType":"Mobile","EstimatedValue":37158},{"PropertyID":480,"CaseMasterID":857,"PropertyType":"Cash","EstimatedValue":134007},{"PropertyID":481,"CaseMasterID":680,"PropertyType":"Jewellery","EstimatedValue":193501},{"PropertyID":482,"CaseMasterID":937,"PropertyType":"Jewellery","EstimatedValue":20619},{"PropertyID":483,"CaseMasterID":638,"PropertyType":"Vehicles","EstimatedValue":463379},{"PropertyID":484,"CaseMasterID":748,"PropertyType":"Documents","EstimatedValue":57900},{"PropertyID":485,"CaseMasterID":532,"PropertyType":"Cash","EstimatedValue":492397},{"PropertyID":486,"CaseMasterID":14,"PropertyType":"Mobile","EstimatedValue":60567},{"PropertyID":487,"CaseMasterID":745,"PropertyType":"Jewellery","EstimatedValue":233729},{"PropertyID":488,"CaseMasterID":542,"PropertyType":"Cash","EstimatedValue":386354},{"PropertyID":489,"CaseMasterID":533,"PropertyType":"Cash","EstimatedValue":33020},{"PropertyID":490,"CaseMasterID":500,"PropertyType":"Cash","EstimatedValue":471694},{"PropertyID":491,"CaseMasterID":422,"PropertyType":"Cash","EstimatedValue":281486},{"PropertyID":492,"CaseMasterID":680,"PropertyType":"Vehicles","EstimatedValue":316988},{"PropertyID":493,"CaseMasterID":957,"PropertyType":"Laptop","EstimatedValue":344253},{"PropertyID":494,"CaseMasterID":782,"PropertyType":"Jewellery","EstimatedValue":293060},{"PropertyID":495,"CaseMasterID":326,"PropertyType":"Laptop","EstimatedValue":259210},{"PropertyID":496,"CaseMasterID":54,"PropertyType":"Documents","EstimatedValue":404348},{"PropertyID":497,"CaseMasterID":485,"PropertyType":"Cash","EstimatedValue":350448},{"PropertyID":498,"CaseMasterID":8,"PropertyType":"Cash","EstimatedValue":273824},{"PropertyID":499,"CaseMasterID":264,"PropertyType":"Cash","EstimatedValue":138354},{"PropertyID":500,"CaseMasterID":512,"PropertyType":"Vehicles","EstimatedValue":206840},{"PropertyID":501,"CaseMasterID":914,"PropertyType":"Laptop","EstimatedValue":40324},{"PropertyID":502,"CaseMasterID":97,"PropertyType":"Documents","EstimatedValue":446674},{"PropertyID":503,"CaseMasterID":439,"PropertyType":"Documents","EstimatedValue":216926},{"PropertyID":504,"CaseMasterID":992,"PropertyType":"Documents","EstimatedValue":258486},{"PropertyID":505,"CaseMasterID":786,"PropertyType":"Documents","EstimatedValue":72578},{"PropertyID":506,"CaseMasterID":657,"PropertyType":"Mobile","EstimatedValue":237314},{"PropertyID":507,"CaseMasterID":429,"PropertyType":"Laptop","EstimatedValue":240660},{"PropertyID":508,"CaseMasterID":859,"PropertyType":"Jewellery","EstimatedValue":198564},{"PropertyID":509,"CaseMasterID":50,"PropertyType":"Mobile","EstimatedValue":279852},{"PropertyID":510,"CaseMasterID":630,"PropertyType":"Laptop","EstimatedValue":119391},{"PropertyID":511,"CaseMasterID":664,"PropertyType":"Laptop","EstimatedValue":325817},{"PropertyID":512,"CaseMasterID":692,"PropertyType":"Laptop","EstimatedValue":231914},{"PropertyID":513,"CaseMasterID":140,"PropertyType":"Jewellery","EstimatedValue":281495},{"PropertyID":514,"CaseMasterID":884,"PropertyType":"Vehicles","EstimatedValue":126375},{"PropertyID":515,"CaseMasterID":632,"PropertyType":"Jewellery","EstimatedValue":284817},{"PropertyID":516,"CaseMasterID":989,"PropertyType":"Jewellery","EstimatedValue":152839},{"PropertyID":517,"CaseMasterID":954,"PropertyType":"Laptop","EstimatedValue":339257},{"PropertyID":518,"CaseMasterID":408,"PropertyType":"Mobile","EstimatedValue":376119},{"PropertyID":519,"CaseMasterID":679,"PropertyType":"Documents","EstimatedValue":15910},{"PropertyID":520,"CaseMasterID":578,"PropertyType":"Jewellery","EstimatedValue":123216},{"PropertyID":521,"CaseMasterID":958,"PropertyType":"Vehicles","EstimatedValue":149437},{"PropertyID":522,"CaseMasterID":697,"PropertyType":"Mobile","EstimatedValue":76750},{"PropertyID":523,"CaseMasterID":173,"PropertyType":"Jewellery","EstimatedValue":489134},{"PropertyID":524,"CaseMasterID":521,"PropertyType":"Jewellery","EstimatedValue":410194},{"PropertyID":525,"CaseMasterID":84,"PropertyType":"Mobile","EstimatedValue":144334},{"PropertyID":526,"CaseMasterID":835,"PropertyType":"Jewellery","EstimatedValue":388773},{"PropertyID":527,"CaseMasterID":181,"PropertyType":"Cash","EstimatedValue":144349},{"PropertyID":528,"CaseMasterID":373,"PropertyType":"Cash","EstimatedValue":197321},{"PropertyID":529,"CaseMasterID":249,"PropertyType":"Mobile","EstimatedValue":415799},{"PropertyID":530,"CaseMasterID":41,"PropertyType":"Documents","EstimatedValue":37351},{"PropertyID":531,"CaseMasterID":206,"PropertyType":"Cash","EstimatedValue":77875},{"PropertyID":532,"CaseMasterID":754,"PropertyType":"Vehicles","EstimatedValue":47652},{"PropertyID":533,"CaseMasterID":41,"PropertyType":"Jewellery","EstimatedValue":264279},{"PropertyID":534,"CaseMasterID":832,"PropertyType":"Documents","EstimatedValue":499945},{"PropertyID":535,"CaseMasterID":705,"PropertyType":"Mobile","EstimatedValue":174185},{"PropertyID":536,"CaseMasterID":863,"PropertyType":"Documents","EstimatedValue":335639},{"PropertyID":537,"CaseMasterID":947,"PropertyType":"Documents","EstimatedValue":424787},{"PropertyID":538,"CaseMasterID":893,"PropertyType":"Documents","EstimatedValue":421100},{"PropertyID":539,"CaseMasterID":216,"PropertyType":"Jewellery","EstimatedValue":179958},{"PropertyID":540,"CaseMasterID":613,"PropertyType":"Jewellery","EstimatedValue":102449},{"PropertyID":541,"CaseMasterID":5,"PropertyType":"Jewellery","EstimatedValue":393537},{"PropertyID":542,"CaseMasterID":798,"PropertyType":"Mobile","EstimatedValue":238204},{"PropertyID":543,"CaseMasterID":311,"PropertyType":"Documents","EstimatedValue":281396},{"PropertyID":544,"CaseMasterID":908,"PropertyType":"Documents","EstimatedValue":407137},{"PropertyID":545,"CaseMasterID":690,"PropertyType":"Jewellery","EstimatedValue":418826},{"PropertyID":546,"CaseMasterID":511,"PropertyType":"Documents","EstimatedValue":146200},{"PropertyID":547,"CaseMasterID":181,"PropertyType":"Vehicles","EstimatedValue":193117},{"PropertyID":548,"CaseMasterID":953,"PropertyType":"Laptop","EstimatedValue":472334},{"PropertyID":549,"CaseMasterID":941,"PropertyType":"Jewellery","EstimatedValue":462685},{"PropertyID":550,"CaseMasterID":206,"PropertyType":"Cash","EstimatedValue":135896},{"PropertyID":551,"CaseMasterID":34,"PropertyType":"Vehicles","EstimatedValue":378210},{"PropertyID":552,"CaseMasterID":459,"PropertyType":"Laptop","EstimatedValue":265131},{"PropertyID":553,"CaseMasterID":15,"PropertyType":"Mobile","EstimatedValue":438095},{"PropertyID":554,"CaseMasterID":857,"PropertyType":"Documents","EstimatedValue":488054},{"PropertyID":555,"CaseMasterID":699,"PropertyType":"Laptop","EstimatedValue":49418},{"PropertyID":556,"CaseMasterID":894,"PropertyType":"Laptop","EstimatedValue":324832},{"PropertyID":557,"CaseMasterID":51,"PropertyType":"Cash","EstimatedValue":393289},{"PropertyID":558,"CaseMasterID":244,"PropertyType":"Vehicles","EstimatedValue":335604},{"PropertyID":559,"CaseMasterID":91,"PropertyType":"Cash","EstimatedValue":493865},{"PropertyID":560,"CaseMasterID":796,"PropertyType":"Documents","EstimatedValue":78844},{"PropertyID":561,"CaseMasterID":480,"PropertyType":"Mobile","EstimatedValue":200411},{"PropertyID":562,"CaseMasterID":148,"PropertyType":"Cash","EstimatedValue":429911},{"PropertyID":563,"CaseMasterID":21,"PropertyType":"Mobile","EstimatedValue":377964},{"PropertyID":564,"CaseMasterID":395,"PropertyType":"Cash","EstimatedValue":477157},{"PropertyID":565,"CaseMasterID":654,"PropertyType":"Documents","EstimatedValue":316822},{"PropertyID":566,"CaseMasterID":261,"PropertyType":"Cash","EstimatedValue":332485},{"PropertyID":567,"CaseMasterID":806,"PropertyType":"Mobile","EstimatedValue":89111},{"PropertyID":568,"CaseMasterID":404,"PropertyType":"Vehicles","EstimatedValue":240541},{"PropertyID":569,"CaseMasterID":204,"PropertyType":"Documents","EstimatedValue":184674},{"PropertyID":570,"CaseMasterID":240,"PropertyType":"Cash","EstimatedValue":198227},{"PropertyID":571,"CaseMasterID":71,"PropertyType":"Mobile","EstimatedValue":390101},{"PropertyID":572,"CaseMasterID":482,"PropertyType":"Jewellery","EstimatedValue":335140},{"PropertyID":573,"CaseMasterID":743,"PropertyType":"Jewellery","EstimatedValue":438975},{"PropertyID":574,"CaseMasterID":522,"PropertyType":"Mobile","EstimatedValue":441636},{"PropertyID":575,"CaseMasterID":211,"PropertyType":"Documents","EstimatedValue":179864},{"PropertyID":576,"CaseMasterID":537,"PropertyType":"Laptop","EstimatedValue":464713},{"PropertyID":577,"CaseMasterID":769,"PropertyType":"Laptop","EstimatedValue":194733},{"PropertyID":578,"CaseMasterID":469,"PropertyType":"Laptop","EstimatedValue":389164},{"PropertyID":579,"CaseMasterID":769,"PropertyType":"Documents","EstimatedValue":351388},{"PropertyID":580,"CaseMasterID":537,"PropertyType":"Jewellery","EstimatedValue":298339},{"PropertyID":581,"CaseMasterID":677,"PropertyType":"Cash","EstimatedValue":189430},{"PropertyID":582,"CaseMasterID":700,"PropertyType":"Documents","EstimatedValue":221705},{"PropertyID":583,"CaseMasterID":870,"PropertyType":"Mobile","EstimatedValue":97743},{"PropertyID":584,"CaseMasterID":791,"PropertyType":"Documents","EstimatedValue":16485},{"PropertyID":585,"CaseMasterID":678,"PropertyType":"Vehicles","EstimatedValue":263126},{"PropertyID":586,"CaseMasterID":16,"PropertyType":"Laptop","EstimatedValue":343745},{"PropertyID":587,"CaseMasterID":59,"PropertyType":"Mobile","EstimatedValue":166594},{"PropertyID":588,"CaseMasterID":272,"PropertyType":"Laptop","EstimatedValue":400816},{"PropertyID":589,"CaseMasterID":97,"PropertyType":"Vehicles","EstimatedValue":145079},{"PropertyID":590,"CaseMasterID":409,"PropertyType":"Mobile","EstimatedValue":466660},{"PropertyID":591,"CaseMasterID":376,"PropertyType":"Documents","EstimatedValue":408635},{"PropertyID":592,"CaseMasterID":194,"PropertyType":"Jewellery","EstimatedValue":123347},{"PropertyID":593,"CaseMasterID":320,"PropertyType":"Jewellery","EstimatedValue":79659},{"PropertyID":594,"CaseMasterID":237,"PropertyType":"Vehicles","EstimatedValue":361049},{"PropertyID":595,"CaseMasterID":57,"PropertyType":"Vehicles","EstimatedValue":35022},{"PropertyID":596,"CaseMasterID":423,"PropertyType":"Cash","EstimatedValue":462464},{"PropertyID":597,"CaseMasterID":424,"PropertyType":"Jewellery","EstimatedValue":116359},{"PropertyID":598,"CaseMasterID":678,"PropertyType":"Cash","EstimatedValue":442958},{"PropertyID":599,"CaseMasterID":29,"PropertyType":"Documents","EstimatedValue":493758},{"PropertyID":600,"CaseMasterID":260,"PropertyType":"Mobile","EstimatedValue":93022}]